dipdup/__init__.py
dipdup/__main__.py
dipdup/abi/__init__.py
dipdup/abi/cairo.py
dipdup/abi/evm.py
dipdup/abi/substrate.py
dipdup/aerich.py
dipdup/api.py
dipdup/cli.py
dipdup/codegen/__init__.py
dipdup/codegen/evm.py
dipdup/codegen/starknet.py
dipdup/codegen/substrate.py
dipdup/codegen/tezos.py
dipdup/config/__init__.py
dipdup/config/_mixin.py
dipdup/config/abi_etherscan.py
dipdup/config/coinbase.py
dipdup/config/evm.py
dipdup/config/evm_blockvision.py
dipdup/config/evm_etherscan.py
dipdup/config/evm_events.py
dipdup/config/evm_node.py
dipdup/config/evm_sourcify.py
dipdup/config/evm_subsquid.py
dipdup/config/evm_transactions.py
dipdup/config/http.py
dipdup/config/ipfs.py
dipdup/config/starknet.py
dipdup/config/starknet_events.py
dipdup/config/starknet_node.py
dipdup/config/starknet_subsquid.py
dipdup/config/substrate.py
dipdup/config/substrate_events.py
dipdup/config/substrate_node.py
dipdup/config/substrate_subscan.py
dipdup/config/substrate_subsquid.py
dipdup/config/tezos.py
dipdup/config/tezos_big_maps.py
dipdup/config/tezos_events.py
dipdup/config/tezos_head.py
dipdup/config/tezos_operations.py
dipdup/config/tezos_token_balances.py
dipdup/config/tezos_token_transfers.py
dipdup/config/tezos_tzkt.py
dipdup/config/tzip_metadata.py
dipdup/context.py
dipdup/database.py
dipdup/datasources/__init__.py
dipdup/datasources/_aiosubstrate.py
dipdup/datasources/_starknetpy.py
dipdup/datasources/_subsquid.py
dipdup/datasources/_web3.py
dipdup/datasources/abi_etherscan.py
dipdup/datasources/coinbase.py
dipdup/datasources/evm_blockvision.py
dipdup/datasources/evm_etherscan.py
dipdup/datasources/evm_node.py
dipdup/datasources/evm_sourcify.py
dipdup/datasources/evm_subsquid.py
dipdup/datasources/http.py
dipdup/datasources/ipfs.py
dipdup/datasources/starknet_node.py
dipdup/datasources/starknet_subsquid.py
dipdup/datasources/substrate_node.py
dipdup/datasources/substrate_subscan.py
dipdup/datasources/substrate_subsquid.py
dipdup/datasources/tezos_tzkt.py
dipdup-8.5.1.dist-info/WHEEL
dipdup-8.5.1.dist-info/entry_points.txt
dipdup-8.5.1.dist-info/METADATA
dipdup-8.5.1.dist-info/RECORD
