Metadata-Version: 2.3
Name: dipdup
Version: 8.5.1
Summary: Modular framework for creating selective indexers and featureful backends for dapps
Keywords: api,backend,blockchain,crypto,cryptocurrencies,dapp,ethereum,evm,framework,indexer,indexers,starknet,sdk,smart-contracts,tezos,web3
Author: Lev Gorodetskii, Vladimir Bobrikov, Michael Zaikin, Igor Sereda
Author-email: Lev Gorodetskii <github@drsr.io>, Vladimir Bobrikov <vladimir_bobrikov@pm.me>, Michael Zaikin <mz@baking-bad.org>, Igor Sereda <sereda.igor.s@gmail.com>
License: MIT
Classifier: Development Status :: 5 - Production/Stable
Classifier: Environment :: Console
Classifier: Intended Audience :: Developers
Classifier: License :: OSI Approved :: MIT License
Classifier: Operating System :: POSIX :: Linux
Classifier: Operating System :: MacOS :: MacOS X
Classifier: Programming Language :: Python :: 3
Classifier: Programming Language :: Python :: 3.12
Classifier: Programming Language :: Python :: Implementation :: CPython
Classifier: Topic :: Software Development :: Libraries :: Application Frameworks
Classifier: Typing :: Typed
Requires-Dist: aiohttp~=3.10
Requires-Dist: aiolimiter~=1.1
Requires-Dist: aiosubstrate~=0.1.0
Requires-Dist: anyio~=4.4
Requires-Dist: appdirs~=1.4
Requires-Dist: apscheduler~=3.10
Requires-Dist: async-lru~=2.0
Requires-Dist: asyncpg~=0.29
Requires-Dist: click~=8.1
Requires-Dist: datamodel-code-generator==0.28.5
Requires-Dist: debugpy>=1.8.15
Requires-Dist: eth-abi~=5.0
Requires-Dist: lru-dict~=1.3
Requires-Dist: mcp~=1.9
Requires-Dist: orjson~=3.10
Requires-Dist: prometheus-client~=0.20
Requires-Dist: pycryptodome~=3.20
Requires-Dist: pydantic~=2.10.3
Requires-Dist: pyhumps~=3.8
Requires-Dist: pysignalr~=1.0
Requires-Dist: python-dotenv~=1.0
Requires-Dist: python-json-logger~=2.0
Requires-Dist: ruamel-yaml~=0.18.6
Requires-Dist: ruff~=0.13.2
Requires-Dist: sentry-sdk~=2.16
Requires-Dist: sqlparse~=0.5
Requires-Dist: starknet-py~=0.28.0
Requires-Dist: strict-rfc3339~=0.7
Requires-Dist: survey~=5.4
Requires-Dist: tabulate~=0.9
Requires-Dist: tortoise-orm==0.25.1
Requires-Dist: uvloop~=0.20
Requires-Dist: web3~=7.2
Requires-Dist: aerich~=0.9.0 ; extra == 'migrations'
Maintainer: Baking Bad team
Maintainer-email: Baking Bad team <hello@baking-bad.org>
Requires-Python: >=3.12, <3.13
Project-URL: Documentation, https://dipdup.io/docs
Project-URL: Homepage, https://dipdup.io/
Project-URL: Repository, https://github.com/dipdup-io/dipdup
Provides-Extra: migrations
